html_email_sender/__init__.py
html_email_sender/sender.py
html_invoice_sender-0.3.dist-info/METADATA
html_invoice_sender-0.3.dist-info/WHEEL
html_invoice_sender-0.3.dist-info/top_level.txt
html_invoice_sender-0.3.dist-info/RECORD
