Metadata-Version: 2.1
Name: html-invoice-sender
Version: 0.3
Requires-Dist: Jinja2
